gitiles/__init__.py
gitiles/cli.py
gitiles/profiles.py
gitiles/ssh_setup.py
gitiles-0.1.1.dist-info/METADATA
gitiles-0.1.1.dist-info/WHEEL
gitiles-0.1.1.dist-info/entry_points.txt
gitiles-0.1.1.dist-info/top_level.txt
gitiles-0.1.1.dist-info/RECORD
