Metadata-Version: 2.1
Name: gitiles
Version: 0.1.1
Summary: A CLI tool to manage multiple Git profiles
Author: Shivam Jain
Author-email: shivamjain.dev@gmail.com
Classifier: Programming Language :: Python :: 3
Classifier: License :: OSI Approved :: MIT License
Classifier: Operating System :: POSIX :: Linux
Requires-Python: >=3.6
